optimum/commands/env.py
optimum/commands/export/neuron.py
optimum/commands/export/neuronx.py
optimum/commands/neuron/base.py
optimum/commands/neuron/cache.py
optimum/commands/neuron/serve.py
optimum/commands/neuron/subcommands.py
optimum/commands/register/register_export.py
optimum/commands/register/register_neuron.py
optimum/exporters/neuron/__init__.py
optimum/exporters/neuron/__main__.py
optimum/exporters/neuron/base.py
optimum/exporters/neuron/config.py
optimum/exporters/neuron/convert.py
optimum/exporters/neuron/model_configs.py
optimum/exporters/neuron/model_wrappers.py
optimum/exporters/neuron/utils.py
optimum/neuron/__init__.py
optimum/neuron/configuration_utils.py
optimum/neuron/hf_argparser.py
optimum/neuron/modeling.py
optimum/neuron/modeling_base.py
optimum/neuron/modeling_diffusion.py
optimum/neuron/modeling_seq2seq.py
optimum/neuron/modeling_traced.py
optimum/neuron/version.py
optimum/neuron/accelerate/__init__.py
optimum/neuron/accelerate/accelerator.py
optimum/neuron/accelerate/optimizer.py
optimum/neuron/accelerate/scheduler.py
optimum/neuron/accelerate/state.py
optimum/neuron/accelerate/utils/__init__.py
optimum/neuron/accelerate/utils/dataclasses.py
optimum/neuron/accelerate/utils/misc.py
optimum/neuron/accelerate/utils/operations.py
optimum/neuron/cache/__init__.py
optimum/neuron/cache/hub_cache.py
optimum/neuron/cache/optimum_neuron_cc_wrapper.py
optimum/neuron/cache/traced.py
optimum/neuron/cache/training.py
optimum/neuron/cache/entries/cache_entry.py
optimum/neuron/cache/entries/multi_model.py
optimum/neuron/cache/entries/single_model.py
optimum/neuron/generation/__init__.py
optimum/neuron/generation/logits_process.py
optimum/neuron/generation/token_selector.py
optimum/neuron/generation/utils.py
optimum/neuron/models/__init__.py
optimum/neuron/models/auto_model.py
optimum/neuron/models/neuron_config.py
optimum/neuron/models/inference/auto_models.py
optimum/neuron/models/inference/modeling_utils.py
optimum_neuron-0.4.1.dist-info/LICENSE
optimum_neuron-0.4.1.dist-info/METADATA
optimum_neuron-0.4.1.dist-info/WHEEL
optimum_neuron-0.4.1.dist-info/entry_points.txt
optimum_neuron-0.4.1.dist-info/top_level.txt
optimum_neuron-0.4.1.dist-info/RECORD
