Metadata-Version: 2.1
Name: optimum-neuron
Version: 0.4.1
Summary: Optimum Neuron serves as the bridge between Hugging Face libraries, such as Transformers, Diffusers, and PEFT, and AWS Trainium and Inferentia accelerators. It provides a set of tools enabling easy model loading, training, and inference on both single and multiple Neuron core configurations, across a wide range of downstream tasks.
Author-email: "HuggingFace Inc. Special Ops Team" <hardware@huggingface.co>
License: Apache-2.0
Project-URL: Homepage, https://huggingface.co/docs/optimum-neuron/index
Keywords: transformers,diffusers,mixed-precision training,fine-tuning,inference,trainium,inferentia,aws
Classifier: Development Status :: 2 - Pre-Alpha
Classifier: License :: OSI Approved :: Apache Software License
Classifier: Intended Audience :: Developers
Classifier: Intended Audience :: Education
Classifier: Intended Audience :: Science/Research
Classifier: Operating System :: OS Independent
Classifier: Programming Language :: Python :: 3.10
Classifier: Topic :: Scientific/Engineering :: Artificial Intelligence
Requires-Python: >=3.10
License-File: LICENSE
Requires-Dist: transformers~=4.55.4
Requires-Dist: accelerate==1.8.1
Requires-Dist: optimum~=1.24.0
Requires-Dist: huggingface-hub>=0.31.4
Requires-Dist: numpy<=1.26.4,>=1.22.2
Requires-Dist: protobuf<4,>=3.20.3
Provides-Extra: diffusers
Requires-Dist: diffusers==0.35.*; extra == "diffusers"
Requires-Dist: peft==0.17.0; extra == "diffusers"
Provides-Extra: diffusers-tests
Requires-Dist: compel==2.1.1; extra == "diffusers-tests"
Provides-Extra: neuron
Requires-Dist: wheel; extra == "neuron"
Requires-Dist: torch-neuron==1.13.1.2.9.74.0; extra == "neuron"
Requires-Dist: torch==1.13.1.*; extra == "neuron"
Requires-Dist: neuron-cc[tensorflow]==1.22.0.0; extra == "neuron"
Requires-Dist: protobuf; extra == "neuron"
Requires-Dist: torchvision; extra == "neuron"
Requires-Dist: numpy==1.22.3; extra == "neuron"
Provides-Extra: neuronx
Requires-Dist: wheel; extra == "neuronx"
Requires-Dist: neuronx-cc==2.21.18209.0; extra == "neuronx"
Requires-Dist: torch-neuronx==2.8.0.2.10.13553; extra == "neuronx"
Requires-Dist: torch==2.8.0.*; extra == "neuronx"
Requires-Dist: torchvision==0.23.*; extra == "neuronx"
Requires-Dist: neuronx-distributed==0.15.22404; extra == "neuronx"
Requires-Dist: libneuronxla==2.2.12677.0; extra == "neuronx"
Provides-Extra: quality
Requires-Dist: pre-commit; extra == "quality"
Requires-Dist: ruff==0.13.0; extra == "quality"
Requires-Dist: isort; extra == "quality"
Provides-Extra: sentence-transformers
Requires-Dist: sentence-transformers>=2.2.0; extra == "sentence-transformers"
Provides-Extra: tests
Requires-Dist: pytest<=8.0.0; extra == "tests"
Requires-Dist: pytest-rerunfailures; extra == "tests"
Requires-Dist: cloudpickle; extra == "tests"
Requires-Dist: pytest-timeout; extra == "tests"
Requires-Dist: pytest-forked; extra == "tests"
Requires-Dist: psutil; extra == "tests"
Requires-Dist: parameterized; extra == "tests"
Requires-Dist: GitPython; extra == "tests"
Requires-Dist: sentencepiece; extra == "tests"
Requires-Dist: datasets; extra == "tests"
Requires-Dist: sacremoses; extra == "tests"
Requires-Dist: safetensors; extra == "tests"
Requires-Dist: sentence-transformers>=2.2.0; extra == "tests"
Requires-Dist: rjieba; extra == "tests"
Requires-Dist: soundfile; extra == "tests"
Requires-Dist: librosa; extra == "tests"
Requires-Dist: controlnet-aux; extra == "tests"
Requires-Dist: torchcodec==0.7.0; extra == "tests"
Provides-Extra: training
Requires-Dist: trl==0.11.4; extra == "training"
Requires-Dist: peft==0.17.0; extra == "training"
Requires-Dist: evaluate==0.4.3; extra == "training"
Provides-Extra: vllm
Requires-Dist: vllm==0.10.2; extra == "vllm"
Provides-Extra: vllm-tests
Requires-Dist: docker; extra == "vllm-tests"
Requires-Dist: pytest-asyncio; extra == "vllm-tests"
Requires-Dist: openai; extra == "vllm-tests"
